{
  "videos": [
    {
      "id": "dtl8pkW54ow",
      "type": "youtube",
      "title": "Medtner, Fairy Tale Op. 20/2 in B minor Campanella",
      "date": "2021-05-23"
    },
    {
      "id": "Z6qnxr03AN8",
      "type": "youtube",
      "title": "Beethoven, Bagatelle op. 126 n° 1, 2 & 3",
      "date": "2023-07-07"
    },
    {
      "id": "8on0pGGTsP4",
      "type": "youtube",
      "title": "Montreal Competition Piano 2021 finals",
      "date": "2021-05-13"
    },
    {
      "id": "ChMzgS1_EQg",
      "type": "youtube",
      "title": "J.S. Bach, Sinfonia 10 in G major, BWV 796",
      "date": "2020-07-11"
    },
    {
      "id": "FsB3RU0VECQ",
      "type": "youtube",
      "title": "Rachmaninov, Prelude Op. 32 No. 5 in G major",
      "date": "2019-12-23"
    },
    {
      "id": "U-deKdT3ITI",
      "type": "youtube",
      "title": "Rachmaninov, Prelude Op. 32 No. 8 in A minor",
      "date": "2019-11-28"
    },
    {
      "id": "CEbYTqO5cAQ",
      "type": "youtube",
      "title": "Beethoven, Piano Sonata No. 30",
      "date": "2019-01-05"
    },
    {
      "id": "N-0EZYlyhl4",
      "type": "youtube",
      "title": "BRAHMS, Intermezzo in e minor, op. 119 n° 2",
      "date": "2018-10-26"
    },
    {
      "id": "EQh7waELTTU",
      "type": "youtube",
      "title": "DEBUSSY, \"Feux d'artifice\" (Préludes, 2ème Livre)",
      "date": "2018-10-26"
    }
  ]
}
